mr_proper/__init__.py
mr_proper/common_types.py
mr_proper/config.py
mr_proper/main.py
mr_proper/public_api.py
mr_proper/pure_validators.py
mr_proper/utils/__init__.py
mr_proper/utils/ast.py
mr_proper/utils/ast_pure.py
mr_proper/utils/python_naming.py
mr_proper-0.0.7.dist-info/LICENSE
mr_proper-0.0.7.dist-info/METADATA
mr_proper-0.0.7.dist-info/WHEEL
mr_proper-0.0.7.dist-info/entry_points.txt
mr_proper-0.0.7.dist-info/top_level.txt
mr_proper-0.0.7.dist-info/RECORD
