Metadata-Version: 2.1
Name: mr-proper
Version: 0.0.7
Summary: Static Python code analyzer, that tries to check if functions in code are pure or not and why.
Home-page: https://github.com/best-doctor/mr_proper
Author: Ilya Lebedev
Author-email: melevir@gmail.com
License: MIT
Keywords: static-analyzer,pure-function
Platform: UNKNOWN
Classifier: Development Status :: 3 - Alpha
Classifier: Environment :: Console
Classifier: Operating System :: OS Independent
Classifier: Topic :: Software Development :: Libraries :: Python Modules
Classifier: Programming Language :: Python
Classifier: Programming Language :: Python :: 3.7
Classifier: Programming Language :: Python :: 3.8
Classifier: Programming Language :: Python :: 3.9
License-File: LICENSE
